pynidus/__init__.py
pynidus/ab.py
pynidus/base.py
pynidus/clients.py
pynidus/errors.py
pynidus-0.1.3.dist-info/LICENSE
pynidus-0.1.3.dist-info/METADATA
pynidus-0.1.3.dist-info/WHEEL
pynidus-0.1.3.dist-info/top_level.txt
pynidus-0.1.3.dist-info/RECORD
