Metadata-Version: 2.1
Name: pynidus
Version: 0.1.3
Summary: A handful of utilities.
Home-page: https://github.com/appchoose/pynidus
Author: Keurcien Luu
Author-email: keurcien@appchoose.io
License: UNKNOWN
Platform: UNKNOWN
Classifier: Programming Language :: Python :: 3
Classifier: License :: OSI Approved :: MIT License
Classifier: Operating System :: OS Independent
Requires-Python: >=3.6
Requires-Dist: bugsnag
Requires-Dist: dill
Requires-Dist: elasticsearch
Requires-Dist: google-cloud-storage
Requires-Dist: pandas
Requires-Dist: psycopg2
Requires-Dist: redis
